{"nodes": [{"id": "c_users_pc_documents_iroooooooonman_iron_man_main_count_py", "label": "count.py", "file_type": "code", "source_file": "C:\\Users\\PC\\Documents\\iroooooooonman\\iron-man-main\\count.py", "source_location": "L1"}], "edges": [{"source": "c_users_pc_documents_iroooooooonman_iron_man_main_count_py", "target": "json", "relation": "imports", "context": "import", "confidence": "EXTRACTED", "source_file": "C:\\Users\\PC\\Documents\\iroooooooonman\\iron-man-main\\count.py", "source_location": "L1", "weight": 1.0}], "raw_calls": []}